severgdocs/README.MD
severgdocs/__init__.py
severgdocs/requirements.txt
severgdocs/thirdparty.json
severgdocs-0.10.dist-info/LICENSE.rst
severgdocs-0.10.dist-info/METADATA
severgdocs-0.10.dist-info/WHEEL
severgdocs-0.10.dist-info/top_level.txt
severgdocs-0.10.dist-info/RECORD
