Metadata-Version: 2.1
Name: severgdocs
Version: 0.10
Summary: Jerrybuilt data exchange through Google Docs - server
Home-page: https://github.com/hansalemaos/severgdocs
Author: Johannes Fischer
Author-email: aulasparticularesdealemaosp@gmail.com
License: MIT
Keywords: data,exchange
Classifier: Development Status :: 4 - Beta
Classifier: Programming Language :: Python :: 3 :: Only
Classifier: Programming Language :: Python :: 3.10
Classifier: Topic :: Software Development :: Libraries :: Python Modules
Classifier: Topic :: Utilities
License-File: LICENSE.rst
Requires-Dist: a-selenium-iframes-crawler
Requires-Dist: beautifulsoup4
Requires-Dist: flatten-any-dict-iterable-or-whatsoever
Requires-Dist: kthread-sleep
Requires-Dist: lxml
Requires-Dist: passprotecttxt
Requires-Dist: requests
Requires-Dist: selenium
Requires-Dist: undetected-chromedriver
